LICENSE.txt
MANIFEST.in
iron_cache.py
setup.py
iron_cache.egg-info/PKG-INFO
iron_cache.egg-info/SOURCES.txt
iron_cache.egg-info/dependency_links.txt
iron_cache.egg-info/requires.txt
iron_cache.egg-info/top_level.txt